nanoplusplus/__init__.py
nanoplusplus/main.py
nanoplusplus-0.3.3.dist-info/LICENSE
nanoplusplus-0.3.3.dist-info/METADATA
nanoplusplus-0.3.3.dist-info/WHEEL
nanoplusplus-0.3.3.dist-info/entry_points.txt
nanoplusplus-0.3.3.dist-info/top_level.txt
nanoplusplus-0.3.3.dist-info/RECORD
