Metadata-Version: 2.1
Name: nanoplusplus
Version: 0.3.3
License-File: LICENSE
Requires-Dist: Click
Requires-Dist: Prompt_Toolkit
Requires-Dist: Pyperclip
